cheshire/__init__.py
cheshire/communication/__init__.py
cheshire/communication/bluetooth.py
cheshire/communication/transmitter.py
cheshire/compiler/compiler.py
cheshire/compiler/state.py
cheshire/generic/__init__.py
cheshire/generic/command.py
cheshire/generic/effect.py
cheshire/generic/platform_command.py
cheshire/hal/__init__.py
cheshire/hal/compilers/__init__.py
cheshire/hal/compilers/ks03_new/__init__.py
cheshire/hal/compilers/ks03_new/compiler.py
cheshire/hal/compilers/ks03_new/constants.py
cheshire/hal/compilers/ks03_new/platform_commands.py
cheshire/hal/compilers/ks03_old/__init__.py
cheshire/hal/compilers/ks03_old/compiler.py
cheshire/hal/compilers/ks03_old/constants.py
cheshire/hal/compilers/ks03_old/platform_commands.py
cheshire/hal/devices.py
cheshire_no_bleak_limit-0.5.7.dist-info/METADATA
cheshire_no_bleak_limit-0.5.7.dist-info/WHEEL
cheshire_no_bleak_limit-0.5.7.dist-info/RECORD
