Metadata-Version: 2.1
Name: cheshire-no-bleak-limit
Version: 0.5.7
Summary: API for Keepsmile, LuckyStyle, Leeleberd, and related smart lights
License: MIT
Author: David
Author-email: davidkuc6@gmail.com
Requires-Python: >=3.10,<3.13
Classifier: License :: OSI Approved :: MIT License
Classifier: Programming Language :: Python :: 3
Classifier: Programming Language :: Python :: 3.10
Classifier: Programming Language :: Python :: 3.11
Classifier: Programming Language :: Python :: 3.12
Requires-Dist: bleak (>=0.21.1)
